README.rst
setup.py
openstreemap/__init__.py
openstreemap/boundary.py
openstreemap/configuration.py
openstreemap/crawler.py
openstreemap/downloader.py
openstreemap/errors.py
openstreemap/extractors.py
openstreemap/outputformatters.py
openstreemap/parsers.py
openstreemap/region.py
openstreemap/transformation.py
openstreemap/version.py
openstreetmap.egg-info/PKG-INFO
openstreetmap.egg-info/SOURCES.txt
openstreetmap.egg-info/dependency_links.txt
openstreetmap.egg-info/requires.txt
openstreetmap.egg-info/top_level.txt